alphabet_thief/__init__.py
alphabet_thief/diacritics.py
alphabet_thief/utils.py
alphabet_thief-0.0.1.dist-info/LICENSE
alphabet_thief-0.0.1.dist-info/METADATA
alphabet_thief-0.0.1.dist-info/WHEEL
alphabet_thief-0.0.1.dist-info/top_level.txt
alphabet_thief-0.0.1.dist-info/RECORD
