Metadata-Version: 2.1
Name: alphabet-thief
Version: 0.0.1
Summary: A tool for deleting Latin alphabets
Author-email: Miyamae Yuichi <yuichi.miyamae.rna@gmail.com>
Project-URL: Homepage, https://github.com/yuichi0625/alphabet-thief
Project-URL: Bug Tracker, https://github.com/yuichi0625/alphabet-thief/issues
Classifier: Programming Language :: Python :: 3
Classifier: License :: OSI Approved :: MIT License
Classifier: Operating System :: OS Independent
Requires-Python: >=3.7
License-File: LICENSE
